LICENSE
MANIFEST.in
README.md
setup.py
switools/ARISTA_ROOT_CA.crt
switools/__init__.py
switools/crc32collision.py
switools/signaturelib.py
switools/swisignature.py
switools/swisigningservice.py
switools/verifyswi.py
switools.egg-info/PKG-INFO
switools.egg-info/SOURCES.txt
switools.egg-info/dependency_links.txt
switools.egg-info/entry_points.txt
switools.egg-info/not-zip-safe
switools.egg-info/requires.txt
switools.egg-info/top_level.txt
swixtools/__init__.py
swixtools/create.py
swixtools/static/schema1.0.json