Metadata-Version: 2.1
Name: switools
Version: 1.2
Summary: Tools for handling Arista SWI/X
Home-page: https://github.com/aristanetworks/swi-tools
License: UNKNOWN
Platform: UNKNOWN
License-File: LICENSE
